py_hot_reload/__init__.py
py_hot_reload/__main__.py
py_hot_reload-1.0.6.dist-info/LICENSE
py_hot_reload-1.0.6.dist-info/METADATA
py_hot_reload-1.0.6.dist-info/WHEEL
py_hot_reload-1.0.6.dist-info/entry_points.txt
py_hot_reload-1.0.6.dist-info/top_level.txt
py_hot_reload-1.0.6.dist-info/RECORD
