Metadata-Version: 2.1
Name: py-hot-reload
Version: 1.0.6
Summary: Python Hot Reload starts the given program and reloads it whenever any file changes in the current directory or imported modules.
Author-email: Heppa Soft <heppasoft@gmail.com>
License: MIT License
Project-URL: Homepage, https://github.com/heppasoft/hot-reload
Project-URL: Bug Tracker, https://github.com/heppasoft/hot-reload/issues
Keywords: reload,hot,hot-reload,hot_reload
Classifier: Development Status :: 5 - Production/Stable
Classifier: Topic :: Utilities
Classifier: License :: OSI Approved :: MIT License
Classifier: Programming Language :: Python
Classifier: Programming Language :: Python :: 3
Classifier: Programming Language :: Python :: 3.6
Classifier: Programming Language :: Python :: 3.7
Classifier: Programming Language :: Python :: 3.8
Classifier: Programming Language :: Python :: 3.9
Classifier: Programming Language :: Python :: 3.10
Classifier: Programming Language :: Python :: 3.11
Requires-Python: >=3.6
License-File: LICENSE
Requires-Dist: watchdog (>=3.0.0)
Requires-Dist: click (>=8.1.3)
